setup.py
voxmart/__init__.py
voxmart/voxmart.py
voxmart.egg-info/PKG-INFO
voxmart.egg-info/SOURCES.txt
voxmart.egg-info/dependency_links.txt
voxmart.egg-info/not-zip-safe
voxmart.egg-info/top_level.txt