Metadata-Version: 2.1
Name: voxmart
Version: 0.0.0.1
Summary: voxmart api manager
Author: ImaniMrosso
